deepomatic/amqp/__init__.py
deepomatic/amqp/client.py
deepomatic/amqp/entities.py
deepomatic/amqp/exceptions.py
deepomatic/rpc/__init__.py
deepomatic/rpc/client.py
deepomatic/rpc/exceptions.py
deepomatic/rpc/response.py
deepomatic/rpc/grpc/__init__.py
deepomatic/rpc/grpc/workflow_client.py
deepomatic/rpc/helpers/__init__.py
deepomatic/rpc/helpers/common.py
deepomatic/rpc/helpers/proto.py
deepomatic/rpc/helpers/v07_proto.py
deepomatic_rpc-0.13.0.dist-info/licenses/LICENCE
deepomatic_rpc-0.13.0.dist-info/METADATA
deepomatic_rpc-0.13.0.dist-info/WHEEL
deepomatic_rpc-0.13.0.dist-info/top_level.txt
deepomatic_rpc-0.13.0.dist-info/RECORD
