Metadata-Version: 2.4
Name: deepomatic-rpc
Version: 0.13.0
Summary: Deepomatic RPC python client
Author-email: deepomatic <support@deepomatic.com>
Project-URL: Homepage, https://github.com/Deepomatic/deepomatic-rpc
Project-URL: Company, https://www.deepomatic.com
Classifier: Programming Language :: Python :: 3.9
Classifier: Programming Language :: Python :: 3
Classifier: Operating System :: OS Independent
Requires-Python: >=3.7
License-File: LICENCE
Requires-Dist: deepomatic-rpc-protobuf~=3.0
Requires-Dist: kombu<6.0.0,>=4.6.0
Requires-Dist: protobuf
Requires-Dist: grpcio<2,>=1.20.1
Dynamic: license-file
